smx10fanctl/__init__.py
smx10fanctl/main.py
smx10fanctl/controllers/__init__.py
smx10fanctl/controllers/auto.py
smx10fanctl/controllers/base.py
smx10fanctl/controllers/set.py
smx10fanctl/core/__init__.py
smx10fanctl/core/coretemp.py
smx10fanctl/core/exc.py
smx10fanctl/core/ipmi.py
smx10fanctl/core/version.py
smx10fanctl-1.0.0.dist-info/LICENSE.md
smx10fanctl-1.0.0.dist-info/METADATA
smx10fanctl-1.0.0.dist-info/WHEEL
smx10fanctl-1.0.0.dist-info/entry_points.txt
smx10fanctl-1.0.0.dist-info/top_level.txt
smx10fanctl-1.0.0.dist-info/RECORD
