Metadata-Version: 2.1
Name: smx10fanctl
Version: 1.0.0
Summary: A fancontroller for Supermicro boards using IPMI raw commands
Home-page: https://github.com/haijeploeg/smx10fanctl
Author: Haije Ploeg
Author-email: ploeg.haije@gmail.com
License: MIT
Platform: UNKNOWN
Requires-Dist: cement (==3.0.4)
Requires-Dist: wheel (>=0.31.0)
Requires-Dist: pyyaml
Requires-Dist: colorlog
Requires-Dist: psutil
